hyh_matrix_algebra/MatrixAlgebra.py
hyh_matrix_algebra/__init__.py
hyh_matrix_algebra/test.py
hyh_matrix_algebra-0.1.dist-info/METADATA
hyh_matrix_algebra-0.1.dist-info/WHEEL
hyh_matrix_algebra-0.1.dist-info/top_level.txt
hyh_matrix_algebra-0.1.dist-info/RECORD
