Metadata-Version: 2.1
Name: hyh-matrix-algebra
Version: 0.1
Summary: basic algebra matrix which implemented add, substract, multiply,etc
Home-page: UNKNOWN
Author: YehangHan
Author-email: test@gmail.com
License: UNKNOWN
Platform: UNKNOWN
